assert_types/__init__.py
assert_types/assert_types.py
assert_types/decorator.py
assert_types-0.1.7.dist-info/DESCRIPTION.rst
assert_types-0.1.7.dist-info/METADATA
assert_types-0.1.7.dist-info/RECORD
assert_types-0.1.7.dist-info/WHEEL
assert_types-0.1.7.dist-info/metadata.json
assert_types-0.1.7.dist-info/top_level.txt
